flake8_error_link.py
flake8_error_link-1.2.4.dist-info/entry_points.txt
flake8_error_link-1.2.4.dist-info/METADATA
flake8_error_link-1.2.4.dist-info/LICENSE
flake8_error_link-1.2.4.dist-info/WHEEL
flake8_error_link-1.2.4.dist-info/RECORD
